jdTextEdit/AutocompleteXML.py
jdTextEdit/Constants.py
jdTextEdit/EncodingList.py
jdTextEdit/Environment.py
jdTextEdit/Functions.py
jdTextEdit/Languages.py
jdTextEdit/LexerList.py
jdTextEdit/Logo.svg
jdTextEdit/Settings.py
jdTextEdit/Updater.py
jdTextEdit/__init__.py
jdTextEdit/__main__.py
jdTextEdit/jdTextEdit.py
jdTextEdit/version.txt
jdTextEdit/api/LanguageBase.py
jdTextEdit/api/SettingsTabBase.py
jdTextEdit/api/SidebarWidgetBase.py
jdTextEdit/api/SignalBase.py
jdTextEdit/api/StatusBarWidgetBase.py
jdTextEdit/api/ThemeBase.py
jdTextEdit/api/Types.py
jdTextEdit/api/__init__.py
jdTextEdit/autocompletion/batch.xml
jdTextEdit/autocompletion/cmake.xml
jdTextEdit/autocompletion/coffee.xml
jdTextEdit/autocompletion/cpp.xml
jdTextEdit/autocompletion/cs.xml
jdTextEdit/autocompletion/css.xml
jdTextEdit/autocompletion/html.xml
jdTextEdit/autocompletion/java.xml
jdTextEdit/autocompletion/javascript.xml
jdTextEdit/autocompletion/lua.xml
jdTextEdit/autocompletion/perl.xml
jdTextEdit/autocompletion/python.xml
jdTextEdit/autocompletion/tex.xml
jdTextEdit/autocompletion/vhdl.xml
jdTextEdit/autocompletion/xml.xml
jdTextEdit/core/BuiltinLanguage.py
jdTextEdit/core/DefaultTheme.py
jdTextEdit/core/FileTheme.py
jdTextEdit/core/Logger.py
jdTextEdit/core/PluginLoader.py
jdTextEdit/core/Project.py
jdTextEdit/core/__init__.py
jdTextEdit/core/api/ApplicationSignals.py
jdTextEdit/core/api/EditorSignals.py
jdTextEdit/core/api/MainWindowSignals.py
jdTextEdit/core/api/PluginAPI.py
jdTextEdit/core/api/ProjectSignals.py
jdTextEdit/core/api/TabWidgetSignals.py
jdTextEdit/core/api/__init__.py
jdTextEdit/data/changelog.html
jdTextEdit/data/translators.json
jdTextEdit/gui/AboutWindow.py
jdTextEdit/gui/ActionSearchWindow.py
jdTextEdit/gui/AddProjectWindow.py
jdTextEdit/gui/CloseSaveWindow.py
jdTextEdit/gui/CodeEdit.py
jdTextEdit/gui/DateTimeWindow.py
jdTextEdit/gui/DayTipWindow.py
jdTextEdit/gui/DebugInfoWindow.py
jdTextEdit/gui/DockWidget.py
jdTextEdit/gui/DocumentStatistics.py
jdtextedit-11.3.dist-info/licenses/LICENSE
jdtextedit-11.3.dist-info/METADATA
jdtextedit-11.3.dist-info/WHEEL
jdtextedit-11.3.dist-info/entry_points.txt
jdtextedit-11.3.dist-info/top_level.txt
jdtextedit-11.3.dist-info/RECORD
