Metadata-Version: 2.4
Name: jdTextEdit
Version: 11.3
Summary: An advanced text editor
Author-email: JakobDev <jakobdev@gmx.de>
License-Expression: GPL-3.0-only
Project-URL: Issues, https://codeberg.org/JakobDev/jdTextEdit/issues
Project-URL: Source, https://codeberg.org/JakobDev/jdTextEdit
Project-URL: Documentation, https://jdtextedit.readthedocs.io
Project-URL: Donation, https://ko-fi.com/jakobdev
Keywords: JakobDev,QScintilla,PyQt,PyQt6,Editor,Texteditor,Macro
Classifier: Development Status :: 5 - Production/Stable
Classifier: Intended Audience :: Developers
Classifier: Intended Audience :: End Users/Desktop
Classifier: Environment :: Other Environment
Classifier: Environment :: X11 Applications :: Qt
Classifier: Natural Language :: English
Classifier: Natural Language :: German
Classifier: Topic :: Text Editors
Classifier: Operating System :: OS Independent
Classifier: Operating System :: POSIX
Classifier: Operating System :: POSIX :: BSD
Classifier: Operating System :: POSIX :: Linux
Classifier: Operating System :: MacOS :: MacOS X
Classifier: Operating System :: Microsoft :: Windows
Classifier: Programming Language :: Python :: 3
Classifier: Programming Language :: Python :: 3.9
Classifier: Programming Language :: Python :: 3.10
Classifier: Programming Language :: Python :: 3.11
Classifier: Programming Language :: Python :: 3.12
Classifier: Programming Language :: Python :: 3.13
Classifier: Programming Language :: Python :: 3 :: Only
Classifier: Programming Language :: Python :: Implementation :: CPython
Requires-Python: >=3.9
License-File: LICENSE
Requires-Dist: PyQt6
Requires-Dist: PyQt6-QScintilla
Requires-Dist: chardet
Requires-Dist: requests
Requires-Dist: jdTranslationHelper
Requires-Dist: EditorConfig
Requires-Dist: pyenchant
Requires-Dist: lxml
Provides-Extra: use-cchardet
Requires-Dist: cchardet; extra == "use-cchardet"
Provides-Extra: use-charset-normalizer
Requires-Dist: charset_normalizer; extra == "use-charset-normalizer"
Dynamic: license-file
